{"nodes": [{"id": "doc_cli_tools", "label": "CLI Tools Reference", "file_type": "markdown", "source_file": "backend/cli-tools/INDEX.md", "description": "Complete guide to all CLI tools with examples, when to use, comparisons (GTT vs Monitor vs Spread)"}], "edges": [{"source": "cli_nf_analyze", "target": "service_technical_analysis", "relation": "uses", "confidence": "EXTRACTED", "confidence_score": 1.0, "source_file": "backend/cli-tools/INDEX.md"}, {"source": "cli_nf_monitor", "target": "monitor_daemon", "relation": "controls", "confidence": "EXTRACTED", "confidence_score": 1.0, "source_file": "backend/cli-tools/INDEX.md"}, {"source": "cli_nf_strategy", "target": "cli_nf_monitor", "relation": "uses", "confidence": "INFERRED", "confidence_score": 0.85, "source_file": "backend/cli-tools/INDEX.md"}, {"source": "cli_nf_backtest", "target": "monitor_rule_evaluator", "relation": "uses", "confidence": "INFERRED", "confidence_score": 0.8, "source_file": "backend/cli-tools/INDEX.md"}, {"source": "doc_cli_tools", "target": "cli_nf_order", "relation": "cites", "confidence": "EXTRACTED", "confidence_score": 1.0, "source_file": "backend/cli-tools/INDEX.md"}, {"source": "doc_cli_tools", "target": "cli_nf_quote", "relation": "cites", "confidence": "EXTRACTED", "confidence_score": 1.0, "source_file": "backend/cli-tools/INDEX.md"}, {"source": "doc_cli_tools", "target": "cli_nf_monitor", "relation": "cites", "confidence": "EXTRACTED", "confidence_score": 1.0, "source_file": "backend/cli-tools/INDEX.md"}], "hyperedges": []}