{"nodes": [{"id": "frontend_v2_app_components_tagsbrowser_jsx", "label": "TagsBrowser.jsx", "file_type": "code", "source_file": "frontend-v2/app/components/TagsBrowser.jsx", "source_location": "L1"}, {"id": "tagsbrowser_buildtaghierarchy", "label": "buildTagHierarchy()", "file_type": "code", "source_file": "frontend-v2/app/components/TagsBrowser.jsx", "source_location": "L13"}, {"id": "tagsbrowser_tagnode", "label": "TagNode()", "file_type": "code", "source_file": "frontend-v2/app/components/TagsBrowser.jsx", "source_location": "L59"}, {"id": "tagsbrowser_tagsbrowser", "label": "TagsBrowser()", "file_type": "code", "source_file": "frontend-v2/app/components/TagsBrowser.jsx", "source_location": "L142"}], "edges": [{"source": "frontend_v2_app_components_tagsbrowser_jsx", "target": "react", "relation": "imports_from", "confidence": "EXTRACTED", "source_file": "frontend-v2/app/components/TagsBrowser.jsx", "source_location": "L1", "weight": 1.0}, {"source": "frontend_v2_app_components_tagsbrowser_jsx", "target": "lucide_react", "relation": "imports_from", "confidence": "EXTRACTED", "source_file": "frontend-v2/app/components/TagsBrowser.jsx", "source_location": "L2", "weight": 1.0}, {"source": "frontend_v2_app_components_tagsbrowser_jsx", "target": "tagsbrowser_buildtaghierarchy", "relation": "contains", "confidence": "EXTRACTED", "source_file": "frontend-v2/app/components/TagsBrowser.jsx", "source_location": "L13", "weight": 1.0}, {"source": "frontend_v2_app_components_tagsbrowser_jsx", "target": "tagsbrowser_tagnode", "relation": "contains", "confidence": "EXTRACTED", "source_file": "frontend-v2/app/components/TagsBrowser.jsx", "source_location": "L59", "weight": 1.0}, {"source": "frontend_v2_app_components_tagsbrowser_jsx", "target": "tagsbrowser_tagsbrowser", "relation": "contains", "confidence": "EXTRACTED", "source_file": "frontend-v2/app/components/TagsBrowser.jsx", "source_location": "L142", "weight": 1.0}], "raw_calls": [{"caller_nid": "tagsbrowser_buildtaghierarchy", "callee": "forEach", "source_file": "frontend-v2/app/components/TagsBrowser.jsx", "source_location": "L16"}, {"caller_nid": "tagsbrowser_buildtaghierarchy", "callee": "convertToArray", "source_file": "frontend-v2/app/components/TagsBrowser.jsx", "source_location": "L53"}, {"caller_nid": "tagsbrowser_tagnode", "callee": "has", "source_file": "frontend-v2/app/components/TagsBrowser.jsx", "source_location": "L61"}, {"caller_nid": "tagsbrowser_tagnode", "callee": "map", "source_file": "frontend-v2/app/components/TagsBrowser.jsx", "source_location": "L116"}, {"caller_nid": "tagsbrowser_tagsbrowser", "callee": "useState", "source_file": "frontend-v2/app/components/TagsBrowser.jsx", "source_location": "L143"}, {"caller_nid": "tagsbrowser_tagsbrowser", "callee": "useMemo", "source_file": "frontend-v2/app/components/TagsBrowser.jsx", "source_location": "L146"}, {"caller_nid": "tagsbrowser_tagsbrowser", "callee": "map", "source_file": "frontend-v2/app/components/TagsBrowser.jsx", "source_location": "L210"}]}