{"nodes": [{"id": "backend_services_scratchpad_db_py", "label": "scratchpad_db.py", "file_type": "code", "source_file": "backend/services/scratchpad_db.py", "source_location": "L1"}, {"id": "scratchpad_db_scratchpaddb", "label": "ScratchpadDB", "file_type": "code", "source_file": "backend/services/scratchpad_db.py", "source_location": "L19"}, {"id": "scratchpad_db_scratchpaddb_init", "label": ".__init__()", "file_type": "code", "source_file": "backend/services/scratchpad_db.py", "source_location": "L22"}, {"id": "scratchpad_db_scratchpaddb_add_entry", "label": ".add_entry()", "file_type": "code", "source_file": "backend/services/scratchpad_db.py", "source_location": "L27"}, {"id": "scratchpad_db_scratchpaddb_get_entries", "label": ".get_entries()", "file_type": "code", "source_file": "backend/services/scratchpad_db.py", "source_location": "L54"}, {"id": "scratchpad_db_scratchpaddb_update_entry", "label": ".update_entry()", "file_type": "code", "source_file": "backend/services/scratchpad_db.py", "source_location": "L82"}, {"id": "scratchpad_db_scratchpaddb_delete_entry", "label": ".delete_entry()", "file_type": "code", "source_file": "backend/services/scratchpad_db.py", "source_location": "L100"}, {"id": "scratchpad_db_scratchpaddb_clear_entries", "label": ".clear_entries()", "file_type": "code", "source_file": "backend/services/scratchpad_db.py", "source_location": "L117"}, {"id": "scratchpad_db_serialize_metadata", "label": "_serialize_metadata()", "file_type": "code", "source_file": "backend/services/scratchpad_db.py", "source_location": "L131"}, {"id": "scratchpad_db_row_to_dict", "label": "_row_to_dict()", "file_type": "code", "source_file": "backend/services/scratchpad_db.py", "source_location": "L137"}, {"id": "scratchpad_db_rationale_1", "label": "DB-backed scratchpad service replacing file-based tools/native/scratchpad.py.  S", "file_type": "rationale", "source_file": "backend/services/scratchpad_db.py", "source_location": "L1"}, {"id": "scratchpad_db_rationale_20", "label": "Async DB-backed scratchpad, thread-specific.", "file_type": "rationale", "source_file": "backend/services/scratchpad_db.py", "source_location": "L20"}, {"id": "scratchpad_db_rationale_34", "label": "Add a new entry. Returns the created entry dict with id.", "file_type": "rationale", "source_file": "backend/services/scratchpad_db.py", "source_location": "L34"}, {"id": "scratchpad_db_rationale_57", "label": "Get all entries for this thread, optionally filtered by type.", "file_type": "rationale", "source_file": "backend/services/scratchpad_db.py", "source_location": "L57"}, {"id": "scratchpad_db_rationale_83", "label": "Update an entry by id. Returns updated entry dict.", "file_type": "rationale", "source_file": "backend/services/scratchpad_db.py", "source_location": "L83"}, {"id": "scratchpad_db_rationale_101", "label": "Delete an entry by id. Returns True if deleted.", "file_type": "rationale", "source_file": "backend/services/scratchpad_db.py", "source_location": "L101"}, {"id": "scratchpad_db_rationale_118", "label": "Delete all entries for this thread. Returns count deleted.", "file_type": "rationale", "source_file": "backend/services/scratchpad_db.py", "source_location": "L118"}], "edges": [{"source": "backend_services_scratchpad_db_py", "target": "json", "relation": "imports", "confidence": "EXTRACTED", "source_file": "backend/services/scratchpad_db.py", "source_location": "L7", "weight": 1.0}, {"source": "backend_services_scratchpad_db_py", "target": "logging", "relation": "imports", "confidence": "EXTRACTED", "source_file": "backend/services/scratchpad_db.py", "source_location": "L8", "weight": 1.0}, {"source": "backend_services_scratchpad_db_py", "target": "datetime", "relation": "imports_from", "confidence": "EXTRACTED", "source_file": "backend/services/scratchpad_db.py", "source_location": "L9", "weight": 1.0}, {"source": "backend_services_scratchpad_db_py", "target": "typing", "relation": "imports_from", "confidence": "EXTRACTED", "source_file": "backend/services/scratchpad_db.py", "source_location": "L10", "weight": 1.0}, {"source": "backend_services_scratchpad_db_py", "target": "sqlalchemy", "relation": "imports_from", "confidence": "EXTRACTED", "source_file": "backend/services/scratchpad_db.py", "source_location": "L12", "weight": 1.0}, {"source": "backend_services_scratchpad_db_py", "target": "database_session", "relation": "imports_from", "confidence": "EXTRACTED", "source_file": "backend/services/scratchpad_db.py", "source_location": "L14", "weight": 1.0}, {"source": "backend_services_scratchpad_db_py", "target": "scratchpad_db_scratchpaddb", "relation": "contains", "confidence": "EXTRACTED", "source_file": "backend/services/scratchpad_db.py", "source_location": "L19", "weight": 1.0}, {"source": "scratchpad_db_scratchpaddb", "target": "scratchpad_db_scratchpaddb_init", "relation": "method", "confidence": "EXTRACTED", "source_file": "backend/services/scratchpad_db.py", "source_location": "L22", "weight": 1.0}, {"source": "scratchpad_db_scratchpaddb", "target": "scratchpad_db_scratchpaddb_add_entry", "relation": "method", "confidence": "EXTRACTED", "source_file": "backend/services/scratchpad_db.py", "source_location": "L27", "weight": 1.0}, {"source": "scratchpad_db_scratchpaddb", "target": "scratchpad_db_scratchpaddb_get_entries", "relation": "method", "confidence": "EXTRACTED", "source_file": "backend/services/scratchpad_db.py", "source_location": "L54", "weight": 1.0}, {"source": "scratchpad_db_scratchpaddb", "target": "scratchpad_db_scratchpaddb_update_entry", "relation": "method", "confidence": "EXTRACTED", "source_file": "backend/services/scratchpad_db.py", "source_location": "L82", "weight": 1.0}, {"source": "scratchpad_db_scratchpaddb", "target": "scratchpad_db_scratchpaddb_delete_entry", "relation": "method", "confidence": "EXTRACTED", "source_file": "backend/services/scratchpad_db.py", "source_location": "L100", "weight": 1.0}, {"source": "scratchpad_db_scratchpaddb", "target": "scratchpad_db_scratchpaddb_clear_entries", "relation": "method", "confidence": "EXTRACTED", "source_file": "backend/services/scratchpad_db.py", "source_location": "L117", "weight": 1.0}, {"source": "backend_services_scratchpad_db_py", "target": "scratchpad_db_serialize_metadata", "relation": "contains", "confidence": "EXTRACTED", "source_file": "backend/services/scratchpad_db.py", "source_location": "L131", "weight": 1.0}, {"source": "backend_services_scratchpad_db_py", "target": "scratchpad_db_row_to_dict", "relation": "contains", "confidence": "EXTRACTED", "source_file": "backend/services/scratchpad_db.py", "source_location": "L137", "weight": 1.0}, {"source": "scratchpad_db_scratchpaddb_add_entry", "target": "scratchpad_db_serialize_metadata", "relation": "calls", "confidence": "EXTRACTED", "source_file": "backend/services/scratchpad_db.py", "source_location": "L47", "weight": 1.0}, {"source": "scratchpad_db_scratchpaddb_add_entry", "target": "scratchpad_db_row_to_dict", "relation": "calls", "confidence": "EXTRACTED", "source_file": "backend/services/scratchpad_db.py", "source_location": "L52", "weight": 1.0}, {"source": "scratchpad_db_scratchpaddb_get_entries", "target": "scratchpad_db_row_to_dict", "relation": "calls", "confidence": "EXTRACTED", "source_file": "backend/services/scratchpad_db.py", "source_location": "L80", "weight": 1.0}, {"source": "scratchpad_db_scratchpaddb_update_entry", "target": "scratchpad_db_row_to_dict", "relation": "calls", "confidence": "EXTRACTED", "source_file": "backend/services/scratchpad_db.py", "source_location": "L98", "weight": 1.0}, {"source": "scratchpad_db_rationale_1", "target": "backend_services_scratchpad_db_py", "relation": "rationale_for", "confidence": "EXTRACTED", "source_file": "backend/services/scratchpad_db.py", "source_location": "L1", "weight": 1.0}, {"source": "scratchpad_db_rationale_20", "target": "scratchpad_db_scratchpaddb", "relation": "rationale_for", "confidence": "EXTRACTED", "source_file": "backend/services/scratchpad_db.py", "source_location": "L20", "weight": 1.0}, {"source": "scratchpad_db_rationale_34", "target": "scratchpad_db_scratchpaddb_add_entry", "relation": "rationale_for", "confidence": "EXTRACTED", "source_file": "backend/services/scratchpad_db.py", "source_location": "L34", "weight": 1.0}, {"source": "scratchpad_db_rationale_57", "target": "scratchpad_db_scratchpaddb_get_entries", "relation": "rationale_for", "confidence": "EXTRACTED", "source_file": "backend/services/scratchpad_db.py", "source_location": "L57", "weight": 1.0}, {"source": "scratchpad_db_rationale_83", "target": "scratchpad_db_scratchpaddb_update_entry", "relation": "rationale_for", "confidence": "EXTRACTED", "source_file": "backend/services/scratchpad_db.py", "source_location": "L83", "weight": 1.0}, {"source": "scratchpad_db_rationale_101", "target": "scratchpad_db_scratchpaddb_delete_entry", "relation": "rationale_for", "confidence": "EXTRACTED", "source_file": "backend/services/scratchpad_db.py", "source_location": "L101", "weight": 1.0}, {"source": "scratchpad_db_rationale_118", "target": "scratchpad_db_scratchpaddb_clear_entries", "relation": "rationale_for", "confidence": "EXTRACTED", "source_file": "backend/services/scratchpad_db.py", "source_location": "L118", "weight": 1.0}], "raw_calls": [{"caller_nid": "scratchpad_db_scratchpaddb_init", "callee": "ValueError", "source_file": "backend/services/scratchpad_db.py", "source_location": "L24"}, {"caller_nid": "scratchpad_db_scratchpaddb_add_entry", "callee": "get_db_context", "source_file": "backend/services/scratchpad_db.py", "source_location": "L35"}, {"caller_nid": "scratchpad_db_scratchpaddb_add_entry", "callee": "execute", "source_file": "backend/services/scratchpad_db.py", "source_location": "L36"}, {"caller_nid": "scratchpad_db_scratchpaddb_add_entry", "callee": "text", "source_file": "backend/services/scratchpad_db.py", "source_location": "L37"}, {"caller_nid": "scratchpad_db_scratchpaddb_add_entry", "callee": "fetchone", "source_file": "backend/services/scratchpad_db.py", "source_location": "L50"}, {"caller_nid": "scratchpad_db_scratchpaddb_add_entry", "callee": "commit", "source_file": "backend/services/scratchpad_db.py", "source_location": "L51"}, {"caller_nid": "scratchpad_db_scratchpaddb_get_entries", "callee": "get_db_context", "source_file": "backend/services/scratchpad_db.py", "source_location": "L58"}, {"caller_nid": "scratchpad_db_scratchpaddb_get_entries", "callee": "execute", "source_file": "backend/services/scratchpad_db.py", "source_location": "L60"}, {"caller_nid": "scratchpad_db_scratchpaddb_get_entries", "callee": "text", "source_file": "backend/services/scratchpad_db.py", "source_location": "L61"}, {"caller_nid": "scratchpad_db_scratchpaddb_get_entries", "callee": "execute", "source_file": "backend/services/scratchpad_db.py", "source_location": "L70"}, {"caller_nid": "scratchpad_db_scratchpaddb_get_entries", "callee": "text", "source_file": "backend/services/scratchpad_db.py", "source_location": "L71"}, {"caller_nid": "scratchpad_db_scratchpaddb_get_entries", "callee": "fetchall", "source_file": "backend/services/scratchpad_db.py", "source_location": "L79"}, {"caller_nid": "scratchpad_db_scratchpaddb_update_entry", "callee": "get_db_context", "source_file": "backend/services/scratchpad_db.py", "source_location": "L84"}, {"caller_nid": "scratchpad_db_scratchpaddb_update_entry", "callee": "execute", "source_file": "backend/services/scratchpad_db.py", "source_location": "L85"}, {"caller_nid": "scratchpad_db_scratchpaddb_update_entry", "callee": "text", "source_file": "backend/services/scratchpad_db.py", "source_location": "L86"}, {"caller_nid": "scratchpad_db_scratchpaddb_update_entry", "callee": "fetchone", "source_file": "backend/services/scratchpad_db.py", "source_location": "L94"}, {"caller_nid": "scratchpad_db_scratchpaddb_update_entry", "callee": "commit", "source_file": "backend/services/scratchpad_db.py", "source_location": "L95"}, {"caller_nid": "scratchpad_db_scratchpaddb_update_entry", "callee": "ValueError", "source_file": "backend/services/scratchpad_db.py", "source_location": "L97"}, {"caller_nid": "scratchpad_db_scratchpaddb_delete_entry", "callee": "get_db_context", "source_file": "backend/services/scratchpad_db.py", "source_location": "L102"}, {"caller_nid": "scratchpad_db_scratchpaddb_delete_entry", "callee": "execute", "source_file": "backend/services/scratchpad_db.py", "source_location": "L103"}, {"caller_nid": "scratchpad_db_scratchpaddb_delete_entry", "callee": "text", "source_file": "backend/services/scratchpad_db.py", "source_location": "L104"}, {"caller_nid": "scratchpad_db_scratchpaddb_delete_entry", "callee": "fetchone", "source_file": "backend/services/scratchpad_db.py", "source_location": "L111"}, {"caller_nid": "scratchpad_db_scratchpaddb_delete_entry", "callee": "commit", "source_file": "backend/services/scratchpad_db.py", "source_location": "L112"}, {"caller_nid": "scratchpad_db_scratchpaddb_delete_entry", "callee": "ValueError", "source_file": "backend/services/scratchpad_db.py", "source_location": "L114"}, {"caller_nid": "scratchpad_db_scratchpaddb_clear_entries", "callee": "get_db_context", "source_file": "backend/services/scratchpad_db.py", "source_location": "L119"}, {"caller_nid": "scratchpad_db_scratchpaddb_clear_entries", "callee": "execute", "source_file": "backend/services/scratchpad_db.py", "source_location": "L120"}, {"caller_nid": "scratchpad_db_scratchpaddb_clear_entries", "callee": "text", "source_file": "backend/services/scratchpad_db.py", "source_location": "L121"}, {"caller_nid": "scratchpad_db_scratchpaddb_clear_entries", "callee": "commit", "source_file": "backend/services/scratchpad_db.py", "source_location": "L127"}, {"caller_nid": "scratchpad_db_serialize_metadata", "callee": "dumps", "source_file": "backend/services/scratchpad_db.py", "source_location": "L134"}, {"caller_nid": "scratchpad_db_row_to_dict", "callee": "isinstance", "source_file": "backend/services/scratchpad_db.py", "source_location": "L139"}, {"caller_nid": "scratchpad_db_row_to_dict", "callee": "loads", "source_file": "backend/services/scratchpad_db.py", "source_location": "L140"}, {"caller_nid": "scratchpad_db_row_to_dict", "callee": "isoformat", "source_file": "backend/services/scratchpad_db.py", "source_location": "L154"}, {"caller_nid": "scratchpad_db_row_to_dict", "callee": "isoformat", "source_file": "backend/services/scratchpad_db.py", "source_location": "L155"}, {"caller_nid": "scratchpad_db_row_to_dict", "callee": "isoformat", "source_file": "backend/services/scratchpad_db.py", "source_location": "L156"}]}